[
  {
    "src": "images/photograpy/Hangzhou_China_2025.jpeg",
    "alt": "Hangzhou, China \u00b7 2025",
    "caption": "Hangzhou, China \u00b7 2025"
  },
  {
    "src": "images/photograpy/Abu_Dhabi_UAE_2024.jpg",
    "alt": "Abu Dhabi, UAE \u00b7 2024",
    "caption": "Abu Dhabi, UAE \u00b7 2024"
  },
  {
    "src": "images/photograpy/Abu_Dhabi_UAE_2024_1.JPG",
    "alt": "Abu Dhabi, UAE \u00b7 2024",
    "caption": "Abu Dhabi, UAE \u00b7 2024"
  },
  {
    "src": "images/photograpy/AbuDhabi_UAE_2024.jpg",
    "alt": "AbuDhabi, UAE \u00b7 2024",
    "caption": "AbuDhabi, UAE \u00b7 2024"
  },
  {
    "src": "images/photograpy/Dubai_UAE_2024.jpeg",
    "alt": "Dubai, UAE \u00b7 2024",
    "caption": "Dubai, UAE \u00b7 2024"
  },
  {
    "src": "images/photograpy/Sharjah_UAE_2024.jpg",
    "alt": "Sharjah, UAE \u00b7 2024",
    "caption": "Sharjah, UAE \u00b7 2024"
  },
  {
    "src": "images/photograpy/Weihai_China_2024_1.jpeg",
    "alt": "Weihai, China \u00b7 2024",
    "caption": "Weihai, China \u00b7 2024"
  },
  {
    "src": "images/photograpy/ Kazbek_Georgia_2023.jpeg",
    "alt": " Kazbek, Georgia \u00b7 2023",
    "caption": " Kazbek, Georgia \u00b7 2023"
  },
  {
    "src": "images/photograpy/Batumi_Georgia_2023.jpeg",
    "alt": "Batumi, Georgia \u00b7 2023",
    "caption": "Batumi, Georgia \u00b7 2023"
  },
  {
    "src": "images/photograpy/Kutaisi_Georgia_2023.jpeg",
    "alt": "Kutaisi, Georgia \u00b7 2023",
    "caption": "Kutaisi, Georgia \u00b7 2023"
  },
  {
    "src": "images/photograpy/Tbilisi_Georgia_2023.jpg",
    "alt": "Tbilisi, Georgia \u00b7 2023",
    "caption": "Tbilisi, Georgia \u00b7 2023"
  },
  {
    "src": "images/photograpy/Yerevan_Armenia_2023.jpeg",
    "alt": "Yerevan, Armenia \u00b7 2023",
    "caption": "Yerevan, Armenia \u00b7 2023"
  }
]